weave/.gitignore
weave/Makefile
weave/__init__.py
weave/py.typed
weave/trace_server_version.py
weave/version.py
weave/agent/__init__.py
weave/agent/agent.py
weave/agent/chat_util.py
weave/agent/console.py
weave/agent/tools.py
weave/chat/chat.py
weave/chat/completions.py
weave/chat/inference_models.py
weave/chat/stream.py
weave/chat/types/_models.py
weave/chat/types/chat_completion.py
weave/chat/types/chat_completion_chunk.py
weave/chat/types/chat_completion_message.py
weave/chat/types/chat_completion_stream_options_param.py
weave/chat/types/chat_completion_token_logprob.py
weave/chat/types/completion_usage.py
weave/chat/types/model.py
weave/chat/types/models.py
weave/compat/wandb/__init__.py
weave/compat/wandb/util/netrc.py
weave/compat/wandb/wandb_thin/__init__.py
weave/compat/wandb/wandb_thin/env.py
weave/compat/wandb/wandb_thin/errors.py
weave/compat/wandb/wandb_thin/internal_api.py
weave/compat/wandb/wandb_thin/login.py
weave/compat/wandb/wandb_thin/termlog.py
weave/compat/wandb/wandb_thin/util.py
weave/dataset/__init__.py
weave/dataset/dataset.py
weave/evaluation/__init__.py
weave/evaluation/eval.py
weave/evaluation/eval_imperative.py
weave/flow/annotation_spec.py
weave/flow/casting.py
weave/flow/leaderboard.py
weave/flow/model.py
weave/flow/monitor.py
weave/flow/saved_view.py
weave/flow/scorer.py
weave/flow/util.py
weave/initialization/__init__.py
weave/initialization/moviepy_video_thread_safety.py
weave/initialization/pil_image_thread_safety.py
weave/integrations/README.md
weave/integrations/__init__.py
weave/integrations/integration_utilities.py
weave/integrations/patch.py
weave/integrations/patcher.py
weave/integrations/anthropic/__init__.py
weave/integrations/anthropic/anthropic_sdk.py
weave/integrations/autogen/__init__.py
weave/integrations/autogen/autogen_sdk.py
weave/integrations/autogen/config.py
weave/integrations/bedrock/__init__.py
weave/integrations/bedrock/bedrock_sdk.py
weave/integrations/cerebras/__init__.py
weave-0.52.24.dist-info/METADATA
weave-0.52.24.dist-info/WHEEL
weave-0.52.24.dist-info/licenses/LICENSE
weave-0.52.24.dist-info/RECORD
