Metadata-Version: 2.4
Name: weave
Version: 0.52.24
Summary: A toolkit for building composable interactive data driven applications.
Project-URL: Company, https://wandb.com
Project-URL: Documentation, https://docs.wandb.com/
Project-URL: Changes, https://github.com/wandb/weave/releases
Project-URL: Source Code, https://github.com/wandb/weave
Project-URL: Issue Tracker, https://github.com/wandb/weave/issues/
Project-URL: Twitter, https://twitter.com/weights_biases
Author-email: Shawn Lewis <shawn@wandb.com>, Tim Sweeney <tim@wandb.com>, Nick Peneranda <nick.penaranda@wandb.com>, Jeff Raubitschek <jeff@wandb.com>, Jamie Rasmussen <jamie.rasmussen@wandb.com>, Griffin Tarpenning <griffin.tarpenning@wandb.com>, Josiah Lee <josiah.lee@wandb.com>, Andrew Truong <andrew@wandb.com>, Niall McQuay <niall.mcquay@wandb.com>
Maintainer-email: W&B <support@wandb.com>
License:                                  Apache License
License-File: LICENSE
Classifier: Development Status :: 4 - Beta
Classifier: Environment :: Web Environment
Classifier: Framework :: Flask
Classifier: Framework :: Jupyter
Classifier: Intended Audience :: Developers
Classifier: Intended Audience :: Science/Research
Classifier: License :: OSI Approved :: Apache Software License
Classifier: Operating System :: OS Independent
Classifier: Programming Language :: Python
Classifier: Topic :: Database :: Front-Ends
Classifier: Topic :: Office/Business :: Financial :: Spreadsheet
Classifier: Topic :: Scientific/Engineering :: Information Analysis
Classifier: Topic :: Scientific/Engineering :: Visualization
Classifier: Topic :: Software Development :: Libraries :: Application Frameworks
Classifier: Topic :: Software Development :: Widget Sets
Requires-Python: >=3.10
Requires-Dist: click
Requires-Dist: diskcache==5.6.3
Requires-Dist: gql[httpx]>=3.0.0
Requires-Dist: jsonschema>=4.23.0
Requires-Dist: packaging>=21.0
Requires-Dist: polyfile-weave
Requires-Dist: pydantic>=2.0.0
Requires-Dist: sentry-sdk<3.0.0,>=2.0.0
Requires-Dist: tenacity!=8.4.0,>=8.3.0
Requires-Dist: tzdata; platform_system == 'Windows'
Requires-Dist: wandb>=0.17.1
Provides-Extra: anthropic
Requires-Dist: anthropic>=0.18.0; extra == 'anthropic'
Provides-Extra: autogen
Requires-Dist: autogen-agentchat>=0.5.7; (python_version >= '3.10') and extra == 'autogen'
Provides-Extra: bedrock
Requires-Dist: boto3; extra == 'bedrock'
Requires-Dist: moto[bedrock]>=5.0.24; extra == 'bedrock'
Provides-Extra: cerebras
Requires-Dist: cerebras-cloud-sdk; extra == 'cerebras'
Provides-Extra: cohere
Requires-Dist: cohere>=5.13.5; extra == 'cohere'
Provides-Extra: crewai
Requires-Dist: crewai-tools>=0.38.0; (python_version >= '3.10' and python_version <= '3.13' and platform_python_implementation != 'PyPy') and extra == 'crewai'
Requires-Dist: crewai<=0.108.0,>=0.100.1; (python_version >= '3.10' and python_version <= '3.13' and platform_python_implementation != 'PyPy') and extra == 'crewai'
Requires-Dist: openai<1.100.0,>=1.99.9; extra == 'crewai'
Provides-Extra: dspy
Requires-Dist: dspy>=3.0.0; (python_version >= '3.10') and extra == 'dspy'
Provides-Extra: google-genai
Requires-Dist: google-genai<=1.23.0,>=1.0.0; (python_version >= '3.10') and extra == 'google-genai'
Requires-Dist: pillow>=11.1.0; extra == 'google-genai'
Provides-Extra: groq
Requires-Dist: groq>=0.13.0; extra == 'groq'
Provides-Extra: huggingface
Requires-Dist: huggingface-hub>=0.28.1; extra == 'huggingface'
Provides-Extra: instructor
Requires-Dist: google-genai>=1.5.0; extra == 'instructor'
Requires-Dist: instructor<1.11.0,>=1.4.3; extra == 'instructor'
Requires-Dist: openai<1.100.0,>=1.99.9; extra == 'instructor'
Provides-Extra: langchain
Requires-Dist: chromadb>=0.5.0; (python_version >= '3.10') and extra == 'langchain'
Requires-Dist: langchain-anthropic>=0.3.15; (python_version >= '3.10') and extra == 'langchain'
Requires-Dist: langchain-cohere>=0.4.5; (python_version >= '3.10') and extra == 'langchain'
Requires-Dist: langchain-community>=0.2.1; (python_version >= '3.10') and extra == 'langchain'
Requires-Dist: langchain-core>=0.2.1; (python_version >= '3.10') and extra == 'langchain'
Requires-Dist: langchain-google-genai>=2.1.5; (python_version >= '3.10') and extra == 'langchain'
Requires-Dist: langchain-google-vertexai>=2.0.24; (platform_python_implementation != 'PyPy' and python_version >= '3.10') and extra == 'langchain'
Requires-Dist: langchain-litellm>=0.2.2; (python_version >= '3.10') and extra == 'langchain'
Requires-Dist: langchain-openai>=0.1.7; (python_version >= '3.10') and extra == 'langchain'
Requires-Dist: openai<1.100.0,>=1.99.9; extra == 'langchain'
Requires-Dist: opentelemetry-exporter-otlp; (python_version >= '3.10') and extra == 'langchain'
Requires-Dist: pysqlite3; (platform_system == 'Linux' and python_version >= '3.10') and extra == 'langchain'
Provides-Extra: langchain-nvidia-ai-endpoints
Requires-Dist: langchain-core>=0.2.1; extra == 'langchain-nvidia-ai-endpoints'
Requires-Dist: langchain-nvidia-ai-endpoints; extra == 'langchain-nvidia-ai-endpoints'
Provides-Extra: litellm
Requires-Dist: litellm>=1.36.1; extra == 'litellm'
Requires-Dist: openai<1.100.0,>=1.99.9; extra == 'litellm'
Provides-Extra: llamaindex
Requires-Dist: llama-index>=0.10.35; extra == 'llamaindex'
Requires-Dist: openai<1.100.0,>=1.99.9; extra == 'llamaindex'
Provides-Extra: mcp
Requires-Dist: mcp[cli]<1.10.0,>=1.6.0; (python_version >= '3.10') and extra == 'mcp'
Provides-Extra: mistral
Requires-Dist: mistralai>=1.0.0; extra == 'mistral'
Provides-Extra: modal
Requires-Dist: modal; extra == 'modal'
Requires-Dist: python-dotenv; extra == 'modal'
Provides-Extra: notdiamond
Requires-Dist: notdiamond>=0.4.9; (platform_python_implementation != 'PyPy' and python_version > '3.10' and python_version < '3.13') and extra == 'notdiamond'
Requires-Dist: pandas>=2.0.0; extra == 'notdiamond'
Provides-Extra: openai
Requires-Dist: openai<1.100.0,>=1.99.9; extra == 'openai'
Provides-Extra: openai-agents
Requires-Dist: openai-agents>=0.0.4; extra == 'openai-agents'
Provides-Extra: presidio
Requires-Dist: presidio-analyzer==2.2.357; (python_version < '3.13') and extra == 'presidio'
Requires-Dist: presidio-anonymizer==2.2.357; (python_version < '3.13') and extra == 'presidio'
Provides-Extra: rich
Requires-Dist: rich; extra == 'rich'
Provides-Extra: scorers
Requires-Dist: huggingface-hub>=0.28.1; extra == 'scorers'
Requires-Dist: levenshtein>=0.26.0; extra == 'scorers'
Requires-Dist: litellm>=1.58; extra == 'scorers'
Requires-Dist: numpy>1.21.0; extra == 'scorers'
Requires-Dist: pip>=20.0; extra == 'scorers'
Requires-Dist: presidio-analyzer>=2.2.0; extra == 'scorers'
Requires-Dist: presidio-anonymizer>=2.2.0; extra == 'scorers'
Requires-Dist: scikit-learn>=1.5.2; extra == 'scorers'
Requires-Dist: sentence-transformers>=3.3.1; extra == 'scorers'
Requires-Dist: sentencepiece>=0.2.0; extra == 'scorers'
Requires-Dist: torch>=2.4.1; extra == 'scorers'
Requires-Dist: transformers>=4.51.1; extra == 'scorers'
Provides-Extra: smolagents
Requires-Dist: huggingface-hub<1.0.0,>=0.28.1; extra == 'smolagents'
Requires-Dist: litellm>=1.58; (python_version >= '3.10') and extra == 'smolagents'
Requires-Dist: openai<1.100.0,>=1.99.9; extra == 'smolagents'
Requires-Dist: smolagents<1.19.0,>=1.17.0; (python_version >= '3.10') and extra == 'smolagents'
Requires-Dist: sqlalchemy>=2.0.38; extra == 'smolagents'
Provides-Extra: trace-server
Requires-Dist: azure-storage-blob<12.26.0,>=12.24.0; extra == 'trace-server'
Requires-Dist: boto3>=1.34.0; extra == 'trace-server'
Requires-Dist: ddtrace>=2.7.0; extra == 'trace-server'
Requires-Dist: emoji>=2.12.1; extra == 'trace-server'
Requires-Dist: google-cloud-storage>=2.7.0; extra == 'trace-server'
Requires-Dist: litellm>=1.36.1; extra == 'trace-server'
Requires-Dist: openinference-semantic-conventions>=0.1.17; extra == 'trace-server'
Requires-Dist: opentelemetry-proto>=1.12.0; extra == 'trace-server'
Requires-Dist: opentelemetry-semantic-conventions-ai>=0.4.3; extra == 'trace-server'
Provides-Extra: verdict
Requires-Dist: verdict>=0.2.3; (platform_python_implementation != 'PyPy' and python_version < '3.13') and extra == 'verdict'
Provides-Extra: verifiers
Requires-Dist: verifiers<0.1.4,>=0.1.3.post0; (python_version >= '3.11') and extra == 'verifiers'
Provides-Extra: vertexai
Requires-Dist: shapely<=2.0.6; (platform_python_implementation != 'PyPy') and extra == 'vertexai'
Requires-Dist: vertexai>=1.70.0; (platform_python_implementation != 'PyPy' and python_version < '3.13') and extra == 'vertexai'
Provides-Extra: video-support
Requires-Dist: moviepy<=1.0.3; extra == 'video-support'
Provides-Extra: wandb
Requires-Dist: wandb>=0.17.1; extra == 'wandb'
